kuberoscli/__init__.py
kuberoscli/endpoints.py
kuberoscli/kuberos_config.py
kuberoscli/kuberoscli.py
kuberoscli/command_group/__init__.py
kuberoscli/command_group/base.py
kuberoscli/command_group/batchjob.py
kuberoscli/command_group/cluster.py
kuberoscli/command_group/config.py
kuberoscli/command_group/deploy.py
kuberoscli/command_group/fleet.py
kuberoscli/command_group/registry.py
kuberos_cli-0.0.1.dist-info/LICENSE
kuberos_cli-0.0.1.dist-info/METADATA
kuberos_cli-0.0.1.dist-info/WHEEL
kuberos_cli-0.0.1.dist-info/entry_points.txt
kuberos_cli-0.0.1.dist-info/top_level.txt
kuberos_cli-0.0.1.dist-info/RECORD
