Metadata-Version: 2.1
Name: kuberos-cli
Version: 0.0.1
Summary: KuebeROS Command Line Tool
Author-email: Yongzhou Zhang <yongzhou.zhang@h-ka.de>
License: Apache License
Project-URL: GitHub, https://github.com/kuberos-io/kuberos-cli
Project-URL: Issue Tracker, https://github.com/kuberos-io/kuberos-cli/issues
Keywords: robotics,ros,kuberos
Classifier: Programming Language :: Python :: 3
Classifier: Development Status :: 3 - Alpha
Classifier: License :: OSI Approved :: Apache Software License
Classifier: Operating System :: OS Independent
Requires-Python: >=3.8
License-File: LICENSE
Requires-Dist: tabulate >=0.9.0
Requires-Dist: requests >=2.22.0
Requires-Dist: argcomplete >=3.0.0
Requires-Dist: PyYAML >=5.3.0
